mantis_python_test_tool/StringUtils.py
mantis_python_test_tool/__init__.py
mantis_python_test_tool-1.0.0.dist-info/METADATA
mantis_python_test_tool-1.0.0.dist-info/WHEEL
mantis_python_test_tool-1.0.0.dist-info/top_level.txt
mantis_python_test_tool-1.0.0.dist-info/RECORD
