Metadata-Version: 2.1
Name: mantis-python-test-tool
Version: 1.0.0
Summary: test utility
Home-page: UNKNOWN
Author: Derya Pelin Deniz
Author-email: deryapelindenizzz@gmail.com
License: UNKNOWN
Keywords: mantis-python-test-tool
Platform: UNKNOWN
